ftrack_qt/__init__.py
ftrack_qt/utils/__init__.py
ftrack_qt/utils/decorators/__init__.py
ftrack_qt/utils/decorators/threading.py
ftrack_qt/utils/layout/__init__.py
ftrack_qt/utils/theme/__init__.py
ftrack_qt/utils/threading/__init__.py
ftrack_qt/utils/widget/__init__.py
ftrack_qt/widgets/__init__.py
ftrack_qt/widgets/accordion/__init__.py
ftrack_qt/widgets/accordion/accordion_widget.py
ftrack_qt/widgets/asset/__init__.py
ftrack_qt/widgets/asset/asset_version_creation_widget.py
ftrack_qt/widgets/asset/asset_version_selection_widget.py
ftrack_qt/widgets/asset/new_asset_input_widget.py
ftrack_qt/widgets/browsers/__init__.py
ftrack_qt/widgets/browsers/entity_browser.py
ftrack_qt/widgets/browsers/file_browser.py
ftrack_qt/widgets/buttons/__init__.py
ftrack_qt/widgets/buttons/circular_button.py
ftrack_qt/widgets/buttons/options_button.py
ftrack_qt/widgets/buttons/progress_button.py
ftrack_qt/widgets/delegate/__init__.py
ftrack_qt/widgets/delegate/asset_version_combo_box_delegate.py
ftrack_qt/widgets/dialogs/__init__.py
ftrack_qt/widgets/dialogs/file_dialog.py
ftrack_qt/widgets/dialogs/modal_dialog.py
ftrack_qt/widgets/dialogs/radio_button_dialog.py
ftrack_qt/widgets/dialogs/scroll_tool_configs_dialog.py
ftrack_qt/widgets/dialogs/styled_dialog.py
ftrack_qt/widgets/dialogs/tab_dialog.py
ftrack_qt/widgets/headers/__init__.py
ftrack_qt/widgets/headers/accordion_header_widget.py
ftrack_qt/widgets/headers/session_header_widget.py
ftrack_qt/widgets/icons/__init__.py
ftrack_qt/widgets/icons/arrow_icon.py
ftrack_qt/widgets/icons/material_icon.py
ftrack_qt/widgets/icons/status_icon.py
ftrack_qt/widgets/info/__init__.py
ftrack_qt/widgets/info/entity_info.py
ftrack_qt/widgets/lines/__init__.py
ftrack_qt/widgets/lines/line_widget.py
ftrack_qt/widgets/lists/__init__.py
ftrack_qt/widgets/lists/asset_list.py
ftrack_qt/widgets/logos/__init__.py
ftrack_qt/widgets/logos/ftrack_logo.py
ftrack_qt/widgets/models/__init__.py
ftrack_qt/widgets/models/table_model.py
ftrack_qt-3.0.0.dist-info/LICENSE.txt
ftrack_qt-3.0.0.dist-info/METADATA
ftrack_qt-3.0.0.dist-info/WHEEL
ftrack_qt-3.0.0.dist-info/RECORD
